djangoldp_tzcld/__init__.py
djangoldp_tzcld/admin.py
djangoldp_tzcld/apps.py
djangoldp_tzcld/djangoldp_settings.py
djangoldp_tzcld/djangoldp_urls.py
djangoldp_tzcld/permissions.py
djangoldp_tzcld/settings.py
djangoldp_tzcld/locale/fr/LC_MESSAGES/django.mo
djangoldp_tzcld/locale/fr/LC_MESSAGES/django.po
djangoldp_tzcld/management/commands/__init__.py
djangoldp_tzcld/management/commands/assign_community_members_to_public_circles.py
djangoldp_tzcld/management/commands/create_community_related_objects.py
djangoldp_tzcld/management/commands/export_rgpd_friendly.py
djangoldp_tzcld/migrations/0001_initial.py
djangoldp_tzcld/migrations/0002_tzcldcommunity_contact_job.py
djangoldp_tzcld/migrations/0003_auto_20220720_1242.py
djangoldp_tzcld/migrations/0004_tzcldprofilejob_tzcldprofilejobemail_tzcldprofilejobphone.py
djangoldp_tzcld/migrations/0005_auto_20230325_1335.py
djangoldp_tzcld/migrations/0006_auto_20230327_1449.py
djangoldp_tzcld/migrations/0007_auto_20230327_1451.py
djangoldp_tzcld/migrations/0008_auto_20230327_1602.py
djangoldp_tzcld/migrations/0009_auto_20230327_1623.py
djangoldp_tzcld/migrations/0010_auto_20230327_1629.py
djangoldp_tzcld/migrations/0011_auto_20230328_1045.py
djangoldp_tzcld/migrations/0012_auto_20230330_1233.py
djangoldp_tzcld/migrations/0013_auto_20230330_1246.py
djangoldp_tzcld/migrations/0014_auto_20230330_1258.py
djangoldp_tzcld/migrations/0015_auto_20230330_1439.py
djangoldp_tzcld/migrations/0016_tzcldcontactmember.py
djangoldp_tzcld/migrations/0017_tzcldcontactmember_community.py
djangoldp_tzcld/migrations/0018_auto_20230406_1755.py
djangoldp_tzcld/migrations/0019_auto_20230414_1634.py
djangoldp_tzcld/migrations/0020_auto_20230417_1242.py
djangoldp_tzcld/migrations/0021_auto_20230510_1232.py
djangoldp_tzcld/migrations/0022_tzcldcommunity_membership_organisation_name.py
djangoldp_tzcld/migrations/0023_auto_20230524_1456.py
djangoldp_tzcld/migrations/0024_auto_20230703_1337.py
djangoldp_tzcld/migrations/0025_auto_20230703_1343.py
djangoldp_tzcld-5.0.0.dist-info/METADATA
djangoldp_tzcld-5.0.0.dist-info/WHEEL
djangoldp_tzcld-5.0.0.dist-info/top_level.txt
djangoldp_tzcld-5.0.0.dist-info/RECORD
