Metadata-Version: 2.1
Name: djangoldp-tzcld
Version: 5.0.0
Summary: djangoldp package for TZCLD
Home-page: https://git.startinblox.com/djangoldp-packages/djangoldp-tzcld
Author: Startin'blox
Author-email: jbaptiste@startinblox.com
License: MIT
Platform: UNKNOWN
Requires-Dist: djangoldp (~=5.0.0)
Requires-Dist: djangoldp-account (~=5.0.0)
Requires-Dist: djangoldp-circle (~=5.0.0)
Requires-Dist: djangoldp-community (~=4.0.1)
Requires-Dist: djangoldp-project (~=5.0.0)
Requires-Dist: djangoldp-conversation (~=5.0.0)
Requires-Dist: djangoldp-profile (~=4.0.0)
Requires-Dist: djangoldp-skill (~=5.0.0)
Requires-Dist: djangoldp-contact (~=4.0.0)
Requires-Dist: djangoldp-joboffer (~=4.0.1)
Requires-Dist: djangoldp-notification (~=5.0.0)
Requires-Dist: pandas (~=2.2.3)
Requires-Dist: openpyxl (~=3.1.5)
Provides-Extra: include_package_data
Requires-Dist: True ; extra == 'include_package_data'
